[{"data":["1_1_1-1-18","1_2_0","1_3_2-1-18","1_4_0","1_5_iu","2_1_3-1-18","2_2_0","2_3_klkk","2_4_0","2_5_jkkj","3_1_4-1-18","3_2_0","3_3_NNN","3_4_4","3_5_KKK","4_1_","4_2_0","4_3_","4_4_0","4_5_"],"version":"1"},{"data":["1_1_","1_2_0","1_3_","1_4_0","1_5_","2_1_","2_2_0","2_3_","2_4_0","2_5_","3_1_","3_2_0","3_3_","3_4_0","3_5_","4_1_1-1-18","4_2_5","4_3_KJJJK","4_4_3","4_5_JKJK"],"version":"2"},{"data":["1_1_1-1-18","1_2_0","1_3_kjjkk","1_4_0","1_5_ouo","2_1_2-1-18","2_2_0","2_3_iuiuiuiui","2_4_0","2_5_hgjgjgj","3_1_","3_2_0","3_3_","3_4_0","3_5_","4_1_2-1-17","4_2_2","4_3_NMNMNMMN","4_4_2","4_5_HGGGH"],"version":"3"}]