[{"data":["1_","2_","3_suicide","4_","5_","6_","7_"],"version":"1"},{"data":["7_"],"version":"2"},{"data":["6_"],"version":"3"},{"data":["6_"],"version":"4"},{"data":["7_"],"version":"5"},{"data":["7_"],"version":"6"},{"data":["7_"],"version":"7"},{"data":["6_"],"version":"8"},{"data":["7_"],"version":"9"},{"data":["7_"],"version":"10"},{"data":["7_"],"version":"11"},{"data":["6_"],"version":"12"},{"data":["6_"],"version":"13"},{"data":["6_"],"version":"14"},{"data":["5_"],"version":"15"},{"data":["5_"],"version":"16"},{"data":["4_","5_","6_","7_"],"version":"17"},{"data":["6_"],"version":"18"},{"data":["6_"],"version":"19"},{"data":["5_"],"version":"20"},{"data":["4_"],"version":"21"},{"data":["5_"],"version":"22"},{"data":["3_suicide"],"version":"23"},{"data":["3_suicide"],"version":"24"},{"data":["3_suicide"],"version":"25"},{"data":["6_"],"version":"26"},{"data":["4_"],"version":"27"},{"data":["5_"],"version":"28"},{"data":["7_"],"version":"29"},{"data":["6_"],"version":"30"},{"data":["1_","2_","3_suicide","4_","5_","6_","7_"],"version":"31"},{"data":["7_"],"version":"32"},{"data":["5_"],"version":"33"},{"data":["6_"],"version":"34"},{"data":["7_"],"version":"35"},{"data":["5_"],"version":"36"},{"data":["5_"],"version":"37"},{"data":["7_"],"version":"38"},{"data":["7_"],"version":"39"},{"data":["6_"],"version":"40"},{"data":["7_"],"version":"41"},{"data":["6_"],"version":"42"},{"data":["7_"],"version":"43"},{"data":["5_"],"version":"44"},{"data":["5_"],"version":"45"},{"data":["5_"],"version":"46"},{"data":["4_"],"version":"47"},{"data":["5_"],"version":"48"},{"data":["3_suicide","4_","5_"],"version":"49"},{"data":["7_"],"version":"50"},{"data":["6_"],"version":"51"},{"data":["1_"],"version":"52"},{"data":["2_"],"version":"53"},{"data":["3_suicide"],"version":"54"},{"data":["5_","6_"],"version":"55"},{"data":["5_"],"version":"56"},{"data":["6_"],"version":"57"},{"data":["6_"],"version":"58"},{"data":["6_"],"version":"59"},{"data":["6_","7_"],"version":"60"},{"data":["5_","6_"],"version":"61"},{"data":["6_","7_"],"version":"62"},{"data":["7_"],"version":"63"},{"data":["6_","7_"],"version":"64"},{"data":["4_","5_"],"version":"65"},{"data":["6_","7_"],"version":"66"},{"data":["5_","6_"],"version":"67"}]