[{"pleasurable":[{"activity":"a","scale":"3","frequency":"Daily"},{"activity":"b","scale":"3","frequency":"A Few Times a Week"},{"activity":"c","scale":"2","frequency":"Once a Week"}],"mastery-oriented":[{"activity":"a","scale":"4","frequency":"Daily"},{"activity":"b","scale":"0","frequency":"A Few Times a Week"},{"activity":"c","scale":"1","frequency":"Once a Week"}],"version":"1","planner":[{"activity":"c","type":"Pleasurable","day":"Saturday"},{"activity":"c","type":"Meaningful","day":"Saturday"},{"activity":"c","type":"Mastery-Oriented","day":"Wednesday"},{"activity":"b","type":"Pleasurable","day":"Thursday"},{"activity":"b","type":"Meaningful","day":"Wednesday"},{"activity":"b","type":"Mastery-Oriented","day":"Saturday"},{"activity":"a","type":"Mastery-Oriented","day":"Friday"},{"activity":"a","type":"Pleasurable","day":"Monday"},{"activity":"a","type":"Pleasurable","day":"Sunday"},{"activity":"a","type":"Meaningful","day":"Monday"}],"meaningful":[{"activity":"a","scale":"1","frequency":"Daily"},{"activity":"b","scale":"2","frequency":"A Few Times a Week"},{"activity":"c","scale":"1","frequency":"Once a Week"}]},{"pleasurable":[{"activity":"a","scale":"1","frequency":"A Few Times a Week"},{"activity":"b","scale":"2","frequency":"Once a Week"},{"activity":"c","scale":"3","frequency":"Less Than Once a Week"}],"mastery-oriented":[{"activity":"a","scale":"1","frequency":"Daily"},{"activity":"b","scale":"2","frequency":"A Few Times a Week"},{"activity":"c","scale":"2","frequency":"Once a Week"}],"version":"2","planner":[{"activity":"c","type":"Pleasurable","day":"Wednesday"},{"activity":"c","type":"Meaningful","day":"Wednesday"},{"activity":"c","type":"Mastery-Oriented","day":"Thursday"},{"activity":"b","type":"Pleasurable","day":"Tuesday"},{"activity":"b","type":"Meaningful","day":"Friday"},{"activity":"b","type":"Meaningful","day":"Thursday"},{"activity":"b","type":"Mastery-Oriented","day":"Thursday"},{"activity":"b","type":"Mastery-Oriented","day":"Wednesday"},{"activity":"a","type":"Pleasurable","day":"Friday"},{"activity":"a","type":"Pleasurable","day":"Wednesday"},{"activity":"a","type":"Meaningful","day":"Saturday"},{"activity":"a","type":"Meaningful","day":"Friday"},{"activity":"a","type":"Mastery-Oriented","day":"Friday"},{"activity":"a","type":"Mastery-Oriented","day":"Wednesday"}],"meaningful":[{"activity":"a","scale":"1","frequency":"Daily"},{"activity":"b","scale":"3","frequency":"A Few Times a Week"},{"activity":"c","scale":"3","frequency":"Once a Week"}]}]